scrap_stock/__init__.py
scrap_stock/scrap_stock.py
scrap_stock-0.0.1.dist-info/METADATA
scrap_stock-0.0.1.dist-info/WHEEL
scrap_stock-0.0.1.dist-info/top_level.txt
scrap_stock-0.0.1.dist-info/RECORD
