Metadata-Version: 2.1
Name: scrap-stock
Version: 0.0.1
Requires-Dist: selenium
Requires-Dist: pandas
